{
    "index": "Q3u98Gz2d4g",
    "title": "Corn Processing in Northeastern China  #shorts #cornprocessing #agriculture",
    "url": "https://www.youtube.com/watch?v=Q3u98Gz2d4g",
    "category": "People & Blogs",
    "tasks": [
        {
            "task": "Contributing to Food Safety and Production in Popcorn Factory",
            "subtasks": [
                "Observing and understanding food safety standards in the factory",
                "Noticing the evolution from dust prevention to liquid sterilization processes",
                "Assisting in the inspection of the production line during the liquid sterilization phase",
                "Monitoring the transportation of products via conveyor belts for quality control",
                "Participating in mixing syrup and processing it through the baking and cooling stages",
                "Supervising the machine-operated filling and sealing of popcorn packages",
                "Ensuring the selection and quality of corn harvested from northeastern China for popcorn production",
                "Promoting the health benefits and traditional flavors of the final product"
            ]
        },
        {
            "task": "Contributing to Food Safety and Production in Popcorn Factory",
            "subtasks": []
        },
        {
            "task": "Contributing to Food Safety and Production in Popcorn Factory",
            "subtasks": [
                "Observing and understanding food safety standards in the factory",
                "Noticing the evolution from dust prevention to liquid sterilization processes",
                "Assisting in the inspection of the production line during the liquid sterilization phase",
                "Monitoring the transportation of products via conveyor belts for quality control",
                "Participating in mixing syrup and processing it through the baking and cooling stages",
                "Supervising the machine-operated filling and sealing of popcorn packages",
                "Ensuring the selection and quality of corn harvested from northeastern China for popcorn production",
                "Promoting the health benefits and traditional flavors of the final product"
            ]
        },
        {
            "task": "MAINTASK: Contributing to Food Safety and Production in Popcorn Factory",
            "subtasks": [
                "Observing and understanding food safety standards in the factory",
                "Noticing the evolution from dust prevention to liquid sterilization processes",
                "Assisting in the inspection of the production line during the liquid sterilization phase",
                "Monitoring the transportation of products via conveyor belts for quality control",
                "Participating in mixing syrup and processing it through the baking and cooling stages",
                "Supervising the machine-operated filling and sealing of popcorn packages",
                "Ensuring the selection and quality of corn harvested from northeastern China for popcorn production",
                "Promoting the health benefits and traditional flavors of the final product"
            ]
        }
    ]
}