{
    "index": "6vhFpQTMGu4",
    "title": "HOW TO USE A BOX BLADE TO REMOVE DIRT #tractors #homesteading #kubota",
    "url": "https://www.youtube.com/watch?v=6vhFpQTMGu4",
    "category": "Education",
    "tasks": [
        {
            "task": "Planting seeds",
            "subtasks": [
                "Walking to the field",
                "Holding the seed packet",
                "Bending down to plant",
                "Inserting seeds into the ground"
            ]
        },
        {
            "task": "Checking on crops",
            "subtasks": [
                "Walking through the rows",
                ".inspecting plants for pests",
                "Monitoring plant growth"
            ]
        },
        {
            "task": "Operating a combine",
            "subtasks": [
                "Going around the crops",
                "Collecting harvested grain",
                "Driving the combine"
            ]
        },
        {
            "task": "Spraying chemicals",
            "subtasks": [
                "Walking with the spray equipment",
                "Aim the sprayer at the plants",
                "Following the rows"
            ]
        },
        {
            "task": "Load grain onto a truck",
            "subtasks": [
                "Driving up to the grain pile",
                "Operating the auger to load grain",
                "Securing the truck"
            ]
        },
        {
            "task": "Repairing farm equipment",
            "subtasks": [
                "Identifying damaged parts",
                "Disassembling the equipment",
                "Applying lubricant or weld",
                "Reassembling the parts"
            ]
        },
        {
            "task": "Feeding animals",
            "subtasks": [
                "Preparing the feed",
                "Transporting the feed to the barn",
                "Distributing the feed to the animals"
            ]
        },
        {
            "task": "Planting seeds",
            "subtasks": [
                "Walking to the field",
                "Holding the seed packet",
                "Bending down to plant",
                "Inserting seeds into the ground"
            ]
        },
        {
            "task": "Checking on crops",
            "subtasks": [
                "Walking through the rows",
                "inspecting plants for pests",
                "Monitoring plant growth"
            ]
        },
        {
            "task": "Operating a combine",
            "subtasks": [
                "Going around the crops",
                "Collecting harvested grain",
                "Driving the combine"
            ]
        },
        {
            "task": "Spraying chemicals",
            "subtasks": [
                "Walking with the spray equipment",
                "Aim the sprayer at the plants",
                "Following the rows"
            ]
        },
        {
            "task": "Load grain onto a truck",
            "subtasks": [
                "Driving up to the grain pile",
                "Operating the auger to load grain",
                "Securing the truck"
            ]
        },
        {
            "task": "Repairing farm equipment",
            "subtasks": [
                "Identifying damaged parts",
                "Disassembling the equipment",
                "Applying lubricant or weld",
                "Reassembling the parts"
            ]
        },
        {
            "task": "Feeding animals",
            "subtasks": [
                "Preparing the feed",
                "Transporting the feed to the barn",
                "Distributing the feed to the animals"
            ]
        }
    ]
}