{
    "index": "dHumorpFUI4",
    "title": "Home made Machine for mixing components and pouring foam polyurethane",
    "url": "https://www.youtube.com/watch?v=dHumorpFUI4",
    "category": "Autos & Vehicles",
    "tasks": [
        {
            "task": "Repeating name",
            "subtasks": [
                "Say name (DimaTorzok) four times in a row"
            ]
        },
        {
            "task": "Patrolling garden",
            "subtasks": [
                "Walk around garden",
                "Check plants for damage",
                "Look for intruders or pests"
            ]
        },
        {
            "task": "Moving camera",
            "subtasks": [
                "Walk around with camera to capture garden shots",
                "Steadify camera while moving"
            ]
        },
        {
            "task": "Assembling fence",
            "subtasks": [
                "Gather materials for fence",
                "Hammer nails into wooden posts",
                "Install wire mesh on fence"
            ]
        },
        {
            "task": "Fixing fence",
            "subtasks": [
                "Identify damaged fence section",
                "Remove old nails",
                "Install new fence panels",
                "Reinforce base with concrete"
            ]
        },
        {
            "task": "Pruning shrubs",
            "subtasks": [
                "Trim overgrown shrubs",
                "Remove dead branches",
                "Shape shrubs for better growth"
            ]
        },
        {
            "task": "Plucking leaves",
            "subtasks": [
                "Select leaves to pluck",
                "Pinch leaves between fingers",
                "Place plucked leaves in basket"
            ]
        },
        {
            "task": "Watering garden",
            "subtasks": [
                "Fill watering can from water source",
                "Walk to garden with watering can",
                "Water plants at base, avoiding foliage"
            ]
        },
        {
            "task": "Edging lawn",
            "subtasks": [
                "Hold edging tool firmly",
                "Following edges of lawn",
                "Remove grass clippings and weeds"
            ]
        },
        {
            "task": "Planting flowers",
            "subtasks": [
                "Select flower bulbs or seeds",
                "Dig holes with trowel",
                "Plant bulbs at appropriate depth",
                "Water newly planted flowers"
            ]
        },
        {
            "task": "Applying mulch",
            "subtasks": [
                "Transport mulch to garden",
                "Spread mulch around plants",
                "Press mulch into soil with hands"
            ]
        },
        {
            "task": "Harvesting vegetables",
            "subtasks": [
                "Identify ripe vegetables",
                "Grip vegetable stem or base",
                "Pull or cut vegetable free",
                "Place harvested vegetables in basket"
            ]
        },
        {
            "task": "Feeding animals",
            "subtasks": [
                "Prepare feeding area",
                "Distribute food to animals",
                "Observe animals while eating"
            ]
        },
        {
            "task": "Collecting eggs",
            "subtasks": [
                "Check chicken coop",
                "Open chicken nesting boxes",
                "Gather eggs, handling carefully"
            ]
        },
        {
            "task": "Collecting honeycomb",
            "subtasks": [
                "Inspect beehive frames",
                "Identify ripe honeycomb cells",
                "Carefully remove honeycomb with smoker"
            ]
        },
        {
            "task": "Feeding chickens",
            "subtasks": [
                "Prepare chicken feed",
                "Distribute feed in containers",
                "Monitor chickens for any illnesses"
            ]
        },
        {
            "task": "Moving furniture",
            "subtasks": [
                "Carry garden furniture to desired location",
                "Arrange furniture around garden",
                "Secure furniture in place"
            ]
        },
        {
            "task": "Cleaning patio",
            "subtasks": [
                "Sweep patio surface",
                "Power wash patio area",
                "Apply sealant, if necessary"
            ]
        },
        {
            "task": "Setting up garden table",
            "subtasks": [
                "Unpack garden table components",
                "Assemble table pieces",
                "Attach table legs"
            ]
        },
        {
            "task": "Watering lawn from top",
            "subtasks": [
                "Adjust sprinkler system",
                "Ensure even water distribution",
                "Monitor water pressure"
            ]
        },
        {
            "task": "Plumbing maintenance",
            "subtasks": [
                "Inspect garden hose connections",
                "Replace damaged hose fittings",
                "Check for leaks in irrigation system"
            ]
        },
        {
            "task": "Repeating name",
            "subtasks": [
                "** Say name (DimaTorzok) four times in a row."
            ]
        },
        {
            "task": "Patrolling garden",
            "subtasks": [
                "**"
            ]
        },
        {
            "task": "Moving camera",
            "subtasks": [
                "**"
            ]
        },
        {
            "task": "Assembling fence",
            "subtasks": [
                "**"
            ]
        },
        {
            "task": "Fixing fence",
            "subtasks": [
                "**"
            ]
        },
        {
            "task": "Pruning shrubs",
            "subtasks": [
                "**"
            ]
        },
        {
            "task": "Plucking leaves",
            "subtasks": [
                "**"
            ]
        },
        {
            "task": "Watering garden",
            "subtasks": [
                "**"
            ]
        },
        {
            "task": "Edging lawn",
            "subtasks": [
                "**"
            ]
        },
        {
            "task": "Planting flowers",
            "subtasks": [
                "**"
            ]
        },
        {
            "task": "Applying mulch",
            "subtasks": [
                "**"
            ]
        },
        {
            "task": "Harvesting vegetables",
            "subtasks": [
                "**"
            ]
        },
        {
            "task": "Feeding animals",
            "subtasks": [
                "**"
            ]
        },
        {
            "task": "Collecting eggs",
            "subtasks": [
                "**"
            ]
        },
        {
            "task": "Collecting honeycomb",
            "subtasks": [
                "**"
            ]
        },
        {
            "task": "Feeding chickens",
            "subtasks": [
                "**"
            ]
        },
        {
            "task": "Moving furniture",
            "subtasks": [
                "**"
            ]
        },
        {
            "task": "Cleaning patio",
            "subtasks": [
                "**"
            ]
        },
        {
            "task": "Setting up garden table",
            "subtasks": [
                "**"
            ]
        },
        {
            "task": "Watering lawn from top",
            "subtasks": [
                "**"
            ]
        },
        {
            "task": "Plumbing maintenance",
            "subtasks": [
                "**"
            ]
        }
    ]
}