{
    "index": "NlOCQg_3wc8",
    "title": "Unknown Title",
    "url": "https://www.youtube.com/watch?v=NlOCQg_3wc8",
    "category": "Unknown Category",
    "tasks": [
        {
            "task": "Farming equipment operation and melon harvesting",
            "subtasks": [
                "Steering the\u519c\u4e1a\u62d6\u62c9\u673a",
                "Operating the melon harvesting attachment on the\u62d6\u62c9\u673a",
                "Navigating the\u62d6\u62c9\u673a through uneven terrain in the\u519c\u7530",
                "Ensuring ripe watermelons are detected and collected by the harvesting attachment"
            ]
        },
        {
            "task": "Melon sorting process",
            "subtasks": [
                "Manually inspecting watermelons for ripeness",
                "Sorting ripe melons from unripe ones on the sorting line",
                "Packaging the sorted ripe watermelons into crates or boxes"
            ]
        },
        {
            "task": "Agricultural processing",
            "subtasks": [
                "Cleaning the harvested watermelons if necessary",
                "Applying any required coatings or treatments to the melons",
                "Stacking or arranging packaged melons for storage or transportation",
                "MAINTASK first, then SUBTASKs under each, separated by new lines. Since the transcript is in Chinese, but given by a user as a translation or summary, I should consider the tasks based on the provided description."
            ]
        },
        {
            "task": "[Primary task]",
            "subtasks": [
                "[Sub-task 1]",
                "[Sub-task 2]"
            ]
        },
        {
            "task": "Operations and Maintenance of Melon Harvesting Equipment",
            "subtasks": [
                "Driving and navigating harvesting equipment through the watermelon field",
                "Monitoring the harvesting function to ensure melons are collected properly",
                "Steering the equipment to reach all areas of the field, adjusting speed and direction"
            ]
        },
        {
            "task": "Melon Sorting and Handling",
            "subtasks": [
                "Inspecting each melon's ripeness (possibly through visual and tactile examination)",
                "Sorting ripe melons from unripe ones on a line (physical act of picking up and placing)",
                "Handling the melons carefully to avoid damage during sorting and transfer"
            ]
        },
        {
            "task": "Packaging of Ripe Melons",
            "subtasks": [
                "Loading the sorted melons into crates or boxes (lifting and positioning)",
                "Ensuring proper arrangement within the packaging to prevent damage during transport"
            ]
        },
        {
            "task": "But based purely on the provided transcript, which includes some repetition (\"Let's go\" multiple times), perhaps indicating movement through different areas of the operation, like from the field to the sorting room. So the last MAINTASK could be relating to driving the equipment to sort the melons if they've already been harvested.",
            "subtasks": [
                ""
            ]
        },
        {
            "task": "Operating Agricultural Equipment for Watermelon Harvesting",
            "subtasks": [
                "Steer the harvester through the watermelon field",
                "Inspect and adjust the harvesting mechanism to pick ripe melons",
                "Maneuver the equipment around obstacles in the field"
            ]
        },
        {
            "task": "Manual Sorting of Watermelons",
            "subtasks": [
                "Walk along the sorting line and check each melon's ripeness",
                "Pick up watermelons from the conveyor and place them in the correct bin",
                "Ensure gentle handling to avoid damaging the melons"
            ]
        },
        {
            "task": "Watermelon Packaging",
            "subtasks": [
                "Lift sorted melons from the bins and place them into crates",
                "Stack the crates neatly to prevent crushing",
                "Seal or cover the crates for transportation"
            ]
        },
        {
            "task": "Driving a Farming Vehicle for Melon Harvesting",
            "subtasks": [
                "Safely operate the vehicle through the melon field",
                "Adjust speed and direction to avoid damaging the crops or equipment",
                "Check machine settings for optimal melon collection"
            ]
        },
        {
            "task": "Manual Melon Ripeness Inspection",
            "subtasks": [
                "Bend over or squat to assess each melon's ripeness (\u53ef\u80fd\u901a\u8fc7\u6572\u51fb\u8046\u542c\u58f0\u97f3\u6216\u89c2\u5bdf\u8272\u6cfd)",
                "Use hands or tools to select ripe melons from the conveyor"
            ]
        },
        {
            "task": "Watermelon Packaging",
            "subtasks": [
                "Lift ripe melons from their holding area (\u53ef\u80fd\u662f\u4f20\u9001\u5e26\u6216\u5176\u4ed6\u5e73\u53f0)",
                "Carefully place the melons into boxes or crates, arranging them neatly",
                "Secure the boxes with necessary straps or seals",
                "However, due to the original transcript being in Chinese and possibly translated, it's possible that some nuances might have been lost. Nonetheless, given the context of the questions and the need to generate tasks based on the provided transcript, these tasks (with their subtasks) capture the core physical activities mentioned or implied. The user mentioned to put the answer in the specified format, with MAINTASKs followed by SUBTASKs. The given answer adheres to this structure and provides a detailed breakdown of the tasks and their components as inferred from the transcript."
            ]
        },
        {
            "task": "Operating Agricultural Equipment for Watermelon Harvesting**",
            "subtasks": [
                "** Steering the harvesting machine through the watermelon field.",
                "** Adjusting the harvesting mechanism to collect ripe melons efficiently.",
                "** Navigating the machine around field obstacles to ensure optimal collection."
            ]
        },
        {
            "task": "Manual Sorting of Watermelons**",
            "subtasks": [
                "** Inspect each melon's ripeness through visual and tactile examination.",
                "** Gently pick up melons from the conveyor and place them into the correct bin.",
                "** Handle melons carefully to prevent damage during transfer."
            ]
        },
        {
            "task": "Watermelon Packaging**",
            "subtasks": [
                "** Lift and arrange sorted melons into crates or boxes.",
                "** Stack the crates neatly to prevent crushing during transport.",
                "** Secure the crates with proper seals or covers."
            ]
        }
    ]
}