{
    "index": "TVGWGjaKyUw",
    "title": "Powerful Tractor Plowing the Field | Farming in Action  #Tractor #TractorPlowing #PlowingTheField",
    "url": "https://www.youtube.com/watch?v=TVGWGjaKyUw",
    "category": "People & Blogs",
    "tasks": [
        {
            "task": "Soaxing Creek",
            "subtasks": [
                "Position self near creek",
                "Prepare soaxing materials",
                "Submerge plants into creek water"
            ]
        },
        {
            "task": "Harvesting crops",
            "subtasks": [
                "Identify ripe crops",
                "Bend over to reach crops",
                "Collect crops into basket"
            ]
        },
        {
            "task": "Moving equipment",
            "subtasks": [
                "Walk from field to storage area",
                "Lift and carry equipment"
            ]
        },
        {
            "task": "Inspection of equipment",
            "subtasks": [
                "Walk around equipment",
                "Check\u5404\u4e2a\u90e8\u4ef6\u72b6\u6001"
            ]
        },
        {
            "task": "Feeding animals",
            "subtasks": [
                "Approach animal enclosure",
                "Open feed bin",
                "Measure\u548cdistribute feed"
            ]
        },
        {
            "task": "Milking animals",
            "subtasks": [
                "Approach dairy animal",
                "Attatch milking\u8bbe\u5907",
                "Milk and collect milk"
            ]
        },
        {
            "task": "Repairing equipment",
            "subtasks": [
                "Identify\u635f\u574f\u7684\u90e8\u4ef6",
                "Retrieve replacement parts",
                "Use tools to repair machinery"
            ]
        },
        {
            "task": "Planting seeds",
            "subtasks": [
                "Walk between rows",
                "Bend over to plant seeds",
                "Cover seeds with soil"
            ]
        },
        {
            "task": "Watering plants",
            "subtasks": [
                "Locate watering can or hose",
                "Walk between plants",
                "Water individual plants"
            ]
        },
        {
            "task": "Applying pesticide",
            "subtasks": [
                "Mix pesticide solution",
                "Spray plants\u5747\u5300"
            ]
        },
        {
            "task": "Checking dairy animal health",
            "subtasks": [
                "Approach animal",
                "Check udder and milk quality",
                "Inspect overall health"
            ]
        },
        {
            "task": "Dairy animal milking routine",
            "subtasks": [
                "Prepare milking area",
                "Perform milking",
                "Store milk in refrigerator"
            ]
        },
        {
            "task": "Managing animal waste",
            "subtasks": [
                "Clean stalls",
                "Dispose of waste properly"
            ]
        },
        {
            "task": "Farm animal feeding schedule",
            "subtasks": [
                "Prepare feed for different animals",
                "Distribute feed at appropriate times"
            ]
        },
        {
            "task": "Equipment maintenance",
            "subtasks": [
                "Clean machinery",
                "Lubricate moving parts",
                "Check oil and fuel levels"
            ]
        },
        {
            "task": "Record-keeping",
            "subtasks": [
                "Update crop planting and harvesting dates",
                "Track animal health and production data"
            ]
        },
        {
            "task": "Crop irrigation scheduling",
            "subtasks": [
                "Monitor soil moisture",
                "Plan irrigation timing and frequency"
            ]
        },
        {
            "task": "Weed control",
            "subtasks": [
                "Identify and remove weeds",
                "Remove debris from fields"
            ]
        },
        {
            "task": "Maintaining animal shelter",
            "subtasks": [
                "Check roof and walls for\u635f\u574f",
                "Clean bedding areas",
                "Ensure proper ventilation"
            ]
        },
        {
            "task": "Animal breeding",
            "subtasks": [
                "Identify breeding animals",
                "Facilitate mating",
                "Ensure proper nutrition during pregnancy"
            ]
        },
        {
            "task": "Processing dairy products",
            "subtasks": [
                "Homogenize and pasteurize milk",
                "Package and store finished products"
            ]
        },
        {
            "task": "Operating machinery",
            "subtasks": [
                "Start and operate\u5927\u578b\u519c\u4e1a\u673a\u68b0",
                "Monitor operation to ensure efficiency and safety"
            ]
        },
        {
            "task": "Facing difficulties during farming",
            "subtasks": [
                "Troubleshoot equipment issues",
                "Deal with pests and diseases"
            ]
        },
        {
            "task": "Soaxing Creek maintenance",
            "subtasks": [
                "Regularly check the creek for silt accumulation",
                "Clear any blockages in the creek to ensure proper water flow"
            ]
        }
    ]
}