{
    "index": "VsPCUwDKESE",
    "title": "Unknown Title",
    "url": "https://www.youtube.com/watch?v=VsPCUwDKESE",
    "category": "Unknown Category",
    "tasks": [
        {
            "task": "Setting up cleaning supplies and work area for sanitation operations.",
            "subtasks": [
                "Displaying sorted items in designated buckets by color.",
                "Sorting dirty cloths and placing them into appropriate color-coded buckets.",
                "Adding cleaning solution to buckets at the end of the week for soaking.",
                "Washing and running individual loads for each color of cloths.",
                "Storing OxiClean solution for soaking aprons and uniforms.",
                "Organizing and distributing personal protective equipment such as shoe covers and garbage bags.",
                "Preparing empty bottles for restocking supplies.",
                "Ensuring the work area organized and efficient for one to four operators."
            ]
        },
        {
            "task": "Preparing garden for cultivation.",
            "subtasks": [
                "Setting up work area in the garden for operations.",
                "Decorating or maintaining the garden area."
            ]
        },
        {
            "task": "Cleaning and organizing work area",
            "subtasks": []
        },
        {
            "task": "Preparing for garden work",
            "subtasks": []
        },
        {
            "task": "Set up and organize a cleaning station.",
            "subtasks": [
                "Sort and process colored cloths.",
                "Prepare cleaning solutions.",
                "Store personal protective equipment.",
                "Organize supplies for multiple operators."
            ]
        },
        {
            "task": "Prepare personal protective equipment distribution.",
            "subtasks": []
        },
        {
            "task": "Establish a sanitized workspace.",
            "subtasks": []
        },
        {
            "task": "Organize operational setup for user operations.",
            "subtasks": []
        },
        {
            "task": "Prepare and maintain work area.",
            "subtasks": [
                "Sort and store sorted items in color-coded buckets.",
                "Soak colored cloths using cleaning solution.",
                "Manage OxiClean solution for cleaning workwear.",
                "Organize and distribute personal protective equipment.",
                "Restock empty bottles for supply management."
            ]
        },
        {
            "task": "Organize operational setup.",
            "subtasks": [
                "Arrange work area for one to four people."
            ]
        },
        {
            "task": "Set up and organize cleaning area.",
            "subtasks": []
        },
        {
            "task": "Setup and organization of cleaning depot.",
            "subtasks": [
                ""
            ]
        },
        {
            "task": "Establish a sanitized workspace**",
            "subtasks": [
                "- **Wipe down and arrange color-coded buckets** for sorted materials (SUBTASK)",
                "- **Prepare cleaning solutions** (e.g., OxiClean) and place them in accessible locations (SUBTASK)",
                "- **Organize personal protective equipment** for easy access (SUBTASK)",
                "- **Restock empty bottles** for supply management (SUBTASK)",
                "- **Arrange the workspace** to accommodate one to four operators efficiently (SUBTASK)"
            ]
        },
        {
            "task": "Establish a sanitized workspace.",
            "subtasks": [
                "Sort and store sorted items in color-coded buckets.",
                "Prepare cleaning solutions and place in designated containers.",
                "Organize personal protective equipment for easy access.",
                "Restock empty bottles for supply management.",
                "Arrange the workspace to accommodate one to four operators."
            ]
        }
    ]
}