{
  "text": "I never thought that four years of undergrad and a two-year master's degree would eventually mean that I am actually professional gate holder but here I am proud of it you know I mean dreams really do come true [Applause] [Applause] [Music] about there'd be two money to do anything so it's not fun the calves are fed now run to the house change and get the kids to their school yeah one of those mornings gotta love Monday before we get into skull and to make a pit stop to get a drink miss Jackson's country boys does what manner she said what she said she's not even on I said but she gave me a penny she gave you a penny okay that's one cent yes since you it's one cent over a dollar it costs 99 cents oh she gave you better she said she was gonna give me nine cents okay baby so got the kids dropped off getting ready to go feed in the mud when my husband gets back he went to help a friend who has dairy steers to take to market and needed an extra trailer so when he gets back we'll talk on the mud we are enjoying a mild 55 degree day even though it's rained an inch and a half this weekend and feeding is absolutely horrendous because of the mud and because we have we still have our cows and calves and smaller Lots because they're not quite done calving basically almost and as soon as they are then we will work I'll run them through the chute and we'll work them and put them out on some larger pasture but you believe how fast that little monkey drinks that milk you're out done look at that anyway so that's what we're doing today got the kids delivered on school co-op sweet home school haven't really talked about that but we do that so on Mondays they go to a co-op and mom gets a day off to do other things like writing because I'm a freelance writer for a progressive farmer and Digital magazine called AG now and for that magazine I also record what I write so if you don't like to read you can click a button and let me read it to you so I got that done today and it is some pictures I don't know y'all it's just always a lot going on here anyway we'll head out in the mud in a minute on this I don't need that I'm just going up the road I almost forgot though that I need to make a phone call business phone call and we don't have a landline because it's not working and our cell phone service is really crappy so I go to the barn to conduct business in my truck so that's amazing yeah a rural internet and cell phone service still no hope one day we'll get by okay off its time done and the wind is whipping out there which is good because when the wind whips the mud starts to dry I mean hopefully and I almost forgot that somebody is coming to get corn tonight that hasn't been bagged yet so I guess he gets to do that and there's an M in my way okay one down nine to go ah I don't know if you remember but a while back I showed um my husband picking corn with his old corn picker well this is after this is what's left after probably I don't know 400 or so bags that we sold at least yeah we still got plenty and this is for deer hunters somebody's gonna ask me that it's for deer hunters so yeah here we go [Music] yeah don't even act like you're tired alright that's done ten bags that need to be closed but um I don't know how to do it my husband has this fancy little knot he does and I haven't mastered it so I figured I'd leave something for him to do yeah there we go everybody's hungry we're a little later feeding today a lot later my husband had to take a load of cab to market for a neighbor yeah this money obviously this is not ideal we have another way right now we would do it but we do the best we can with what we have I've seen it worse but this isn't isn't good and another fun thing over the last few years I have been able to add something else to my resume gate holding extraordinaire I never thought that four years of undergrad and a two-year master's degree would eventually mean that I am actually professional gate holder but here I am proud of it you know I mean dreams really do come true and the Sun came out maybe for more than 30 seconds and the winds blowing so that's what we need [Applause] [Music] [Applause] and this will do it pretty van y'all [Music] [Applause] [Applause] [Music] you",
  "segments": [
    {
      "id": 0,
      "start": 0.0,
      "end": 6.14,
      "text": "I never thought that four years of"
    },
    {
      "id": 1,
      "start": 2.73,
      "end": 8.73,
      "text": "undergrad and a two-year master's degree"
    },
    {
      "id": 2,
      "start": 6.14,
      "end": 11.99,
      "text": "would eventually mean that I am actually"
    },
    {
      "id": 3,
      "start": 8.73,
      "end": 16.109,
      "text": "professional gate holder but here I am"
    },
    {
      "id": 4,
      "start": 11.99,
      "end": 19.13,
      "text": "proud of it you know I mean dreams"
    },
    {
      "id": 5,
      "start": 16.109,
      "end": 19.13,
      "text": "really do come true"
    },
    {
      "id": 6,
      "start": 19.3,
      "end": 22.789,
      "text": "[Applause]"
    },
    {
      "id": 7,
      "start": 26.55,
      "end": 41.769,
      "text": "[Applause]"
    },
    {
      "id": 8,
      "start": 26.77,
      "end": 43.969,
      "text": "[Music]"
    },
    {
      "id": 9,
      "start": 41.769,
      "end": 49.039,
      "text": "about there'd be two money to do"
    },
    {
      "id": 10,
      "start": 43.969,
      "end": 51.829,
      "text": "anything so it's not fun the calves are"
    },
    {
      "id": 11,
      "start": 49.039,
      "end": 56.089,
      "text": "fed now run to the house change and get"
    },
    {
      "id": 12,
      "start": 51.829,
      "end": 57.079,
      "text": "the kids to their school yeah one of"
    },
    {
      "id": 13,
      "start": 56.089,
      "end": 60.409,
      "text": "those mornings"
    },
    {
      "id": 14,
      "start": 57.079,
      "end": 63.11,
      "text": "gotta love Monday before we get into"
    },
    {
      "id": 15,
      "start": 60.409,
      "end": 68.36,
      "text": "skull and to make a pit stop to get a"
    },
    {
      "id": 16,
      "start": 63.11,
      "end": 74.39,
      "text": "drink miss Jackson's country boys does"
    },
    {
      "id": 17,
      "start": 68.36,
      "end": 75.95,
      "text": "what manner she said what she said she's"
    },
    {
      "id": 18,
      "start": 74.39,
      "end": 79.759,
      "text": "not even on I said but she gave me a"
    },
    {
      "id": 19,
      "start": 75.95,
      "end": 82.46,
      "text": "penny she gave you a penny okay that's"
    },
    {
      "id": 20,
      "start": 79.759,
      "end": 85.58,
      "text": "one cent yes since you it's one cent"
    },
    {
      "id": 21,
      "start": 82.46,
      "end": 87.56,
      "text": "over a dollar it costs 99 cents oh she"
    },
    {
      "id": 22,
      "start": 85.58,
      "end": 88.819,
      "text": "gave you better she said she was gonna"
    },
    {
      "id": 23,
      "start": 87.56,
      "end": 96.069,
      "text": "give me nine cents"
    },
    {
      "id": 24,
      "start": 88.819,
      "end": 98.119,
      "text": "okay baby so got the kids dropped off"
    },
    {
      "id": 25,
      "start": 96.069,
      "end": 100.119,
      "text": "getting ready to go feed in the mud when"
    },
    {
      "id": 26,
      "start": 98.119,
      "end": 103.009,
      "text": "my husband gets back he went to help a"
    },
    {
      "id": 27,
      "start": 100.119,
      "end": 106.789,
      "text": "friend who has dairy steers to take to"
    },
    {
      "id": 28,
      "start": 103.009,
      "end": 108.17,
      "text": "market and needed an extra trailer so"
    },
    {
      "id": 29,
      "start": 106.789,
      "end": 112.81,
      "text": "when he gets back we'll talk on the mud"
    },
    {
      "id": 30,
      "start": 108.17,
      "end": 116.569,
      "text": "we are enjoying a mild 55 degree day"
    },
    {
      "id": 31,
      "start": 112.81,
      "end": 120.28,
      "text": "even though it's rained an inch and a"
    },
    {
      "id": 32,
      "start": 116.569,
      "end": 123.77,
      "text": "half this weekend and feeding is"
    },
    {
      "id": 33,
      "start": 120.28,
      "end": 125.509,
      "text": "absolutely horrendous because of the mud"
    },
    {
      "id": 34,
      "start": 123.77,
      "end": 129.979,
      "text": "and because we have we still have our"
    },
    {
      "id": 35,
      "start": 125.509,
      "end": 133.22,
      "text": "cows and calves and smaller Lots because"
    },
    {
      "id": 36,
      "start": 129.979,
      "end": 135.23,
      "text": "they're not quite done calving basically"
    },
    {
      "id": 37,
      "start": 133.22,
      "end": 136.91,
      "text": "almost and as soon as they are then we"
    },
    {
      "id": 38,
      "start": 135.23,
      "end": 139.55,
      "text": "will work I'll run them through the"
    },
    {
      "id": 39,
      "start": 136.91,
      "end": 142.97,
      "text": "chute and we'll work them and put them"
    },
    {
      "id": 40,
      "start": 139.55,
      "end": 145.3,
      "text": "out on some larger pasture but you"
    },
    {
      "id": 41,
      "start": 142.97,
      "end": 147.19,
      "text": "believe how fast that little monkey"
    },
    {
      "id": 42,
      "start": 145.3,
      "end": 152.959,
      "text": "drinks that milk"
    },
    {
      "id": 43,
      "start": 147.19,
      "end": 155.54,
      "text": "you're out done look at that anyway so"
    },
    {
      "id": 44,
      "start": 152.959,
      "end": 159.14,
      "text": "that's what we're doing today got the"
    },
    {
      "id": 45,
      "start": 155.54,
      "end": 160.58,
      "text": "kids delivered on school co-op sweet"
    },
    {
      "id": 46,
      "start": 159.14,
      "end": 163.73,
      "text": "home school haven't really talked about"
    },
    {
      "id": 47,
      "start": 160.58,
      "end": 166.61,
      "text": "that but we do that so on Mondays they"
    },
    {
      "id": 48,
      "start": 163.73,
      "end": 169.34,
      "text": "go to a co-op and mom gets a day off to"
    },
    {
      "id": 49,
      "start": 166.61,
      "end": 170.99,
      "text": "do other things like writing because I'm"
    },
    {
      "id": 50,
      "start": 169.34,
      "end": 172.06,
      "text": "a freelance writer for a progressive"
    },
    {
      "id": 51,
      "start": 170.99,
      "end": 175.15,
      "text": "farmer and"
    },
    {
      "id": 52,
      "start": 172.06,
      "end": 177.4,
      "text": "Digital magazine called AG now and for"
    },
    {
      "id": 53,
      "start": 175.15,
      "end": 179.68,
      "text": "that magazine I also record what I write"
    },
    {
      "id": 54,
      "start": 177.4,
      "end": 181.66,
      "text": "so if you don't like to read you can"
    },
    {
      "id": 55,
      "start": 179.68,
      "end": 184.78,
      "text": "click a button and let me read it to you"
    },
    {
      "id": 56,
      "start": 181.66,
      "end": 187.66,
      "text": "so I got that done today and it is some"
    },
    {
      "id": 57,
      "start": 184.78,
      "end": 193.42,
      "text": "pictures I don't know y'all it's just"
    },
    {
      "id": 58,
      "start": 187.66,
      "end": 194.739,
      "text": "always a lot going on here anyway we'll"
    },
    {
      "id": 59,
      "start": 193.42,
      "end": 196.3,
      "text": "head out in the mud in a minute on this"
    },
    {
      "id": 60,
      "start": 194.739,
      "end": 198.55,
      "text": "I don't need that I'm just going up the"
    },
    {
      "id": 61,
      "start": 196.3,
      "end": 201.64,
      "text": "road I almost forgot though that I need"
    },
    {
      "id": 62,
      "start": 198.55,
      "end": 204.76,
      "text": "to make a phone call business phone call"
    },
    {
      "id": 63,
      "start": 201.64,
      "end": 208.0,
      "text": "and we don't have a landline because"
    },
    {
      "id": 64,
      "start": 204.76,
      "end": 211.36,
      "text": "it's not working and our cell phone"
    },
    {
      "id": 65,
      "start": 208.0,
      "end": 217.209,
      "text": "service is really crappy so I go to the"
    },
    {
      "id": 66,
      "start": 211.36,
      "end": 218.23,
      "text": "barn to conduct business in my truck so"
    },
    {
      "id": 67,
      "start": 217.209,
      "end": 220.63,
      "text": "that's amazing"
    },
    {
      "id": 68,
      "start": 218.23,
      "end": 224.86,
      "text": "yeah a rural internet and cell phone"
    },
    {
      "id": 69,
      "start": 220.63,
      "end": 229.569,
      "text": "service still no hope one day we'll get"
    },
    {
      "id": 70,
      "start": 224.86,
      "end": 232.989,
      "text": "by okay off its time done and the wind"
    },
    {
      "id": 71,
      "start": 229.569,
      "end": 236.5,
      "text": "is whipping out there which is good"
    },
    {
      "id": 72,
      "start": 232.989,
      "end": 242.35,
      "text": "because when the wind whips the mud"
    },
    {
      "id": 73,
      "start": 236.5,
      "end": 244.209,
      "text": "starts to dry I mean hopefully and I"
    },
    {
      "id": 74,
      "start": 242.35,
      "end": 248.95,
      "text": "almost forgot that somebody is coming to"
    },
    {
      "id": 75,
      "start": 244.209,
      "end": 252.459,
      "text": "get corn tonight that hasn't been bagged"
    },
    {
      "id": 76,
      "start": 248.95,
      "end": 261.81,
      "text": "yet so I guess he gets to do that and"
    },
    {
      "id": 77,
      "start": 252.459,
      "end": 266.11,
      "text": "there's an M in my way okay one down"
    },
    {
      "id": 78,
      "start": 261.81,
      "end": 270.88,
      "text": "nine to go ah I don't know if you"
    },
    {
      "id": 79,
      "start": 266.11,
      "end": 272.74,
      "text": "remember but a while back I showed um my"
    },
    {
      "id": 80,
      "start": 270.88,
      "end": 277.87,
      "text": "husband picking corn with his old corn"
    },
    {
      "id": 81,
      "start": 272.74,
      "end": 282.01,
      "text": "picker well this is after this is what's"
    },
    {
      "id": 82,
      "start": 277.87,
      "end": 286.09,
      "text": "left after probably I don't know 400 or"
    },
    {
      "id": 83,
      "start": 282.01,
      "end": 288.82,
      "text": "so bags that we sold at least yeah we"
    },
    {
      "id": 84,
      "start": 286.09,
      "end": 290.52,
      "text": "still got plenty and this is for deer"
    },
    {
      "id": 85,
      "start": 288.82,
      "end": 295.74,
      "text": "hunters somebody's gonna ask me that"
    },
    {
      "id": 86,
      "start": 290.52,
      "end": 305.68,
      "text": "it's for deer hunters so yeah here we go"
    },
    {
      "id": 87,
      "start": 295.74,
      "end": 308.19,
      "text": "[Music]"
    },
    {
      "id": 88,
      "start": 305.68,
      "end": 312.49,
      "text": "yeah don't even act like you're tired"
    },
    {
      "id": 89,
      "start": 308.19,
      "end": 314.979,
      "text": "alright that's done ten bags that need"
    },
    {
      "id": 90,
      "start": 312.49,
      "end": 317.289,
      "text": "to be closed but um I don't know how to"
    },
    {
      "id": 91,
      "start": 314.979,
      "end": 320.05,
      "text": "do it my husband has this fancy little"
    },
    {
      "id": 92,
      "start": 317.289,
      "end": 322.6,
      "text": "knot he does and I haven't mastered it"
    },
    {
      "id": 93,
      "start": 320.05,
      "end": 328.38,
      "text": "so I figured I'd leave something for him"
    },
    {
      "id": 94,
      "start": 322.6,
      "end": 331.66,
      "text": "to do yeah there we go"
    },
    {
      "id": 95,
      "start": 328.38,
      "end": 335.41,
      "text": "everybody's hungry we're a little later"
    },
    {
      "id": 96,
      "start": 331.66,
      "end": 338.169,
      "text": "feeding today a lot later my husband had"
    },
    {
      "id": 97,
      "start": 335.41,
      "end": 342.46,
      "text": "to take a load of cab to market for a"
    },
    {
      "id": 98,
      "start": 338.169,
      "end": 346.63,
      "text": "neighbor yeah this money obviously this"
    },
    {
      "id": 99,
      "start": 342.46,
      "end": 349.33,
      "text": "is not ideal we have another way right"
    },
    {
      "id": 100,
      "start": 346.63,
      "end": 351.479,
      "text": "now we would do it but we do the best we"
    },
    {
      "id": 101,
      "start": 349.33,
      "end": 356.59,
      "text": "can with what we have"
    },
    {
      "id": 102,
      "start": 351.479,
      "end": 358.74,
      "text": "I've seen it worse but this isn't isn't"
    },
    {
      "id": 103,
      "start": 356.59,
      "end": 358.74,
      "text": "good"
    },
    {
      "id": 104,
      "start": 374.85,
      "end": 381.51,
      "text": "and another fun thing over the last few"
    },
    {
      "id": 105,
      "start": 378.75,
      "end": 385.44,
      "text": "years I have been able to add something"
    },
    {
      "id": 106,
      "start": 381.51,
      "end": 389.79,
      "text": "else to my resume gate holding"
    },
    {
      "id": 107,
      "start": 385.44,
      "end": 393.18,
      "text": "extraordinaire I never thought that four"
    },
    {
      "id": 108,
      "start": 389.79,
      "end": 396.09,
      "text": "years of undergrad and a two-year"
    },
    {
      "id": 109,
      "start": 393.18,
      "end": 398.31,
      "text": "master's degree would eventually mean"
    },
    {
      "id": 110,
      "start": 396.09,
      "end": 402.05,
      "text": "that I am actually professional gate"
    },
    {
      "id": 111,
      "start": 398.31,
      "end": 406.1,
      "text": "holder but here I am proud of it you"
    },
    {
      "id": 112,
      "start": 402.05,
      "end": 411.48,
      "text": "know I mean dreams really do come true"
    },
    {
      "id": 113,
      "start": 406.1,
      "end": 414.86,
      "text": "and the Sun came out maybe for more than"
    },
    {
      "id": 114,
      "start": 411.48,
      "end": 418.34,
      "text": "30 seconds and the winds blowing so"
    },
    {
      "id": 115,
      "start": 414.86,
      "end": 418.34,
      "text": "that's what we need"
    },
    {
      "id": 116,
      "start": 428.15,
      "end": 431.67,
      "text": "[Applause]"
    },
    {
      "id": 117,
      "start": 431.45,
      "end": 439.1,
      "text": "[Music]"
    },
    {
      "id": 118,
      "start": 431.67,
      "end": 439.1,
      "text": "[Applause]"
    },
    {
      "id": 119,
      "start": 442.29,
      "end": 446.04,
      "text": "and this will do it pretty van y'all"
    },
    {
      "id": 120,
      "start": 445.87,
      "end": 449.139,
      "text": "[Music]"
    },
    {
      "id": 121,
      "start": 446.04,
      "end": 449.139,
      "text": "[Applause]"
    },
    {
      "id": 122,
      "start": 451.16,
      "end": 459.699,
      "text": "[Applause]"
    },
    {
      "id": 123,
      "start": 451.59,
      "end": 459.699,
      "text": "[Music]"
    },
    {
      "id": 124,
      "start": 461.15,
      "end": 463.21,
      "text": "you"
    }
  ],
  "language": "en"
}